tests/__init__.py
tests/conftest.py
tests/test_cli.py
tests/test_container_cmd.py
tests/test_container_operations.py
tests/test_db.py
tests/test_models.py
tests/test_repository.py
tests/test_user_config.py
tests/test_vllm_client.py
vllmoni/__init__.py
vllmoni/app/db.py
vllmoni/app/models.py
vllmoni/app/repository.py
vllmoni/cli/cli.py
vllmoni/conf/defaults.yaml
vllmoni/conf/model/_default.yaml
vllmoni/conf/model/a100_80gb_pcie/gemma3-27b.yaml
vllmoni/conf/model/a100_80gb_pcie/gemma9b.yaml
vllmoni/conf/model/a100_80gb_pcie/gpt-20b.yaml
vllmoni/conf/model/a100_80gb_pcie/llama_3_1.yaml
vllmoni/conf/model/a100_80gb_pcie/llama_3_1_dida.yaml
vllmoni/conf/model/a100_80gb_pcie/llama_3_1_full.yaml
vllmoni/conf/model/a100_80gb_pcie/llama_3_3.yaml
vllmoni/conf/model/a100_80gb_pcie/llama_finetuned.yaml
vllmoni/conf/model/a100_80gb_pcie/llama_small.yaml
vllmoni/conf/model/a100_80gb_pcie/phi35mini.yaml
vllmoni/conf/model/a100_80gb_pcie/qwen_25.yaml
vllmoni/conf/model/a100_80gb_pcie/qwq.yaml
vllmoni/conf/model/a100_80gb_pcie/xlam-8b.yaml
vllmoni/conf/model/a40/gemma3-27b.yaml
vllmoni/conf/model/a40/gemma9b.yaml
vllmoni/conf/model/a40/gpt-20b.yaml
vllmoni/conf/model/a40/llama_3_1.yaml
vllmoni/conf/model/a40/llama_3_1_dida.yaml
vllmoni/conf/model/a40/llama_3_1_full.yaml
vllmoni/conf/model/a40/llama_3_3.yaml
vllmoni/conf/model/a40/llama_finetuned.yaml
vllmoni/conf/model/a40/llama_small.yaml
vllmoni/conf/model/a40/phi35mini.yaml
vllmoni/conf/model/a40/qwen_25.yaml
vllmoni/conf/model/a40/qwq.yaml
vllmoni/conf/model/a40/xlam-8b.yaml
vllmoni/conf/model/h100_nvl/gemma3-27b.yaml
vllmoni/conf/model/h100_nvl/gemma9b.yaml
vllmoni/conf/model/h100_nvl/gpt-20b.yaml
vllmoni/conf/model/h100_nvl/llama_3_1.yaml
vllmoni/conf/model/h100_nvl/llama_3_1_dida.yaml
vllmoni/conf/model/h100_nvl/llama_3_1_full.yaml
vllmoni/conf/model/h100_nvl/llama_3_3.yaml
vllmoni/conf/model/h100_nvl/llama_finetuned.yaml
vllmoni/conf/model/h100_nvl/llama_small.yaml
vllmoni/conf/model/h100_nvl/phi35mini.yaml
vllmoni-0.1.6.2.dist-info/licenses/LICENSE
vllmoni-0.1.6.2.dist-info/METADATA
vllmoni-0.1.6.2.dist-info/WHEEL
vllmoni-0.1.6.2.dist-info/entry_points.txt
vllmoni-0.1.6.2.dist-info/top_level.txt
vllmoni-0.1.6.2.dist-info/RECORD
