Metadata-Version: 2.4
Name: vllmoni
Version: 0.1.6.2
Summary: A CLI tool for monitoring and managing VLLM inference servers in Docker containers
Requires-Python: >=3.12
License-File: LICENSE
Requires-Dist: docker>=7.1.0
Requires-Dist: dotenv>=0.9.9
Requires-Dist: fastapi>=0.116.0
Requires-Dist: hydra-core>=1.3.2
Requires-Dist: pyyaml>=6.0.0
Requires-Dist: requests>=2.31.0
Requires-Dist: sqlalchemy>=2.0.41
Requires-Dist: toml>=0.10.2
Requires-Dist: typer>=0.16.0
Requires-Dist: uvicorn>=0.35.0
Requires-Dist: pre-commit>=3.4.0
Provides-Extra: test
Requires-Dist: pytest>=8.0.0; extra == "test"
Requires-Dist: pytest-cov>=4.1.0; extra == "test"
Requires-Dist: pytest-mock>=3.12.0; extra == "test"
Dynamic: license-file
